poni2006/__init__.py
poni2006/info.py
poni2006/version.py
poni2006/clean/fig10.csv
poni2006/clean/fig2.csv
poni2006/clean/fig3.csv
poni2006/clean/fig4.csv
poni2006/clean/fig5.csv
poni2006/clean/fig7.csv
poni2006/clean/fig7_legend.csv
poni2006/clean/fig8.csv
poni2006/clean/fig9.csv
poni2006/clean/info.json
poni2006/clean/readme.rst
poni2006/clean/weather_hourly.csv
poni2006-1.2.0.dist-info/AUTHORS.rst
poni2006-1.2.0.dist-info/LICENSE
poni2006-1.2.0.dist-info/METADATA
poni2006-1.2.0.dist-info/WHEEL
poni2006-1.2.0.dist-info/top_level.txt
poni2006-1.2.0.dist-info/RECORD
